tests/__init__.py
tests/test_text2pix.py
text2pix/__init__.py
text2pix-2025.5.100903.dist-info/licenses/LICENSE
text2pix-2025.5.100903.dist-info/METADATA
text2pix-2025.5.100903.dist-info/WHEEL
text2pix-2025.5.100903.dist-info/top_level.txt
text2pix-2025.5.100903.dist-info/RECORD
